<?xml version="1.0" encoding="windows-1252" ?>
<!DOCTYPE ViewObject SYSTEM "jbo_03_01.dtd">
<!---->
<ViewObject
  xmlns="http://xmlns.oracle.com/bc4j"
  Name="KeyAccountActionView"
  Version="11.1.1.59.23"
  SelectList="TraxEventContentOwner.ID, 
       TraxEventContentOwner.CONTENT_OWNER_ID, 
       TraxEventContentOwner.EVENT_ID, 
       TraxEvent.EVENT_TYPE, 
       TraxEvent.EVENT_NAME, 
       TraxEvent.EVENT_DATE, 
       TraxEvent.DESCRIPTION, 
       TraxEvent.NOTE, 
       TraxEvent.CREATED_BY, 
       TraxEvent.CREATED_DATE, 
       TraxEvent.LAST_UPDATED_BY, 
       TraxEvent.LAST_UPDATED_DATE, 
       TraxEvent.ID AS ID1"
  FromList="TRAX_EVENT_CONTENT_OWNER TraxEventContentOwner
INNER JOIN TRAX_EVENT TraxEvent ON (TraxEventContentOwner.EVENT_ID = TraxEvent.ID)"
  Where="TraxEventContentOwner.EVENT_ID = TraxEvent.ID"
  BindingStyle="OracleName"
  CustomQuery="false"
  PageIterMode="Partial"
  UseGlueCode="false"
  RowClass="com.pq.tracs.model.vo.KeyAccountActionViewRowImpl"
  FetchMode="FETCH_AS_NEEDED"
  FetchSize="30"
  ComponentClass="com.pq.tracs.model.vo.PRMView"
  RangeSize="25">
  <DesignTime>
    <Attr Name="_isCodegen" Value="true"/>
  </DesignTime>
  <Properties>
    <SchemaBasedProperties>
      <LABEL
        ResId="com.pq.tracs.model.vo.KeyAccountActionView_LABEL"/>
    </SchemaBasedProperties>
  </Properties>
  <EntityUsage
    Name="TraxEventContentOwner"
    Entity="com.pq.tracs.model.eo.TraxEventContentOwner"/>
  <EntityUsage
    Name="TraxEvent"
    Entity="com.pq.tracs.model.eo.TraxEvent"
    Association="com.pq.tracs.model.ao.EventToEventContentOwnerFkAssoc"
    AssociationEnd="com.pq.tracs.model.ao.EventToEventContentOwnerFkAssoc.TraxEvent"
    SourceUsage="com.pq.tracs.model.vo.KeyAccountActionView.TraxEventContentOwner"
    JoinType="INNER JOIN"
    DeleteParticipant="false">
    <DesignTime>
      <AttrArray Name="_srcAttributes">
        <Item Value="com.pq.tracs.model.eo.TraxEventContentOwner.EventId"/>
      </AttrArray>
      <AttrArray Name="_dstAttributes">
        <Item Value="com.pq.tracs.model.eo.TraxEvent.Id"/>
      </AttrArray>
    </DesignTime>
  </EntityUsage>
  <ViewAttribute
    Name="Id"
    IsNotNull="true"
    PrecisionRule="true"
    EntityAttrName="Id"
    EntityUsage="TraxEventContentOwner"
    AliasName="ID"/>
  <ViewAttribute
    Name="ContentOwnerId"
    IsNotNull="true"
    PrecisionRule="true"
    EntityAttrName="ContentOwnerId"
    EntityUsage="TraxEventContentOwner"
    AliasName="CONTENT_OWNER_ID">
    <Properties>
      <SchemaBasedProperties>
        <LABEL
          ResId="com.pq.tracs.model.vo.KeyAccountActionView.ContentOwnerId_LABEL"/>
      </SchemaBasedProperties>
    </Properties>
  </ViewAttribute>
  <ViewAttribute
    Name="EventId"
    IsNotNull="true"
    PrecisionRule="true"
    EntityAttrName="EventId"
    EntityUsage="TraxEventContentOwner"
    AliasName="EVENT_ID">
    <Properties>
      <SchemaBasedProperties>
        <LABEL
          ResId="com.pq.tracs.model.vo.KeyAccountActionView.EventId_LABEL"/>
      </SchemaBasedProperties>
    </Properties>
  </ViewAttribute>
  <ViewAttribute
    Name="EventType"
    IsNotNull="true"
    PrecisionRule="true"
    EntityAttrName="EventType"
    EntityUsage="TraxEvent"
    AliasName="EVENT_TYPE">
    <Properties>
      <SchemaBasedProperties>
        <LABEL
          ResId="com.pq.tracs.model.vo.KeyAccountActionView.EventType_LABEL"/>
        <DISPLAYWIDTH
          Value="30"/>
      </SchemaBasedProperties>
    </Properties>
  </ViewAttribute>
  <ViewAttribute
    Name="EventName"
    IsNotNull="true"
    PrecisionRule="true"
    EntityAttrName="EventName"
    EntityUsage="TraxEvent"
    AliasName="EVENT_NAME">
    <Properties>
      <SchemaBasedProperties>
        <LABEL
          ResId="com.pq.tracs.model.vo.KeyAccountActionView.EventName_LABEL"/>
        <DISPLAYWIDTH
          Value="30"/>
      </SchemaBasedProperties>
    </Properties>
  </ViewAttribute>
  <ViewAttribute
    Name="EventDate"
    PrecisionRule="true"
    EntityAttrName="EventDate"
    EntityUsage="TraxEvent"
    AliasName="EVENT_DATE">
    <Properties>
      <SchemaBasedProperties>
        <FMT_FORMATTER
          ResId="com.pq.tracs.model.vo.KeyAccountActionView.EventDate_FMT_FORMATTER"/>
        <FMT_FORMAT
          ResId="com.pq.tracs.model.vo.KeyAccountActionView.EventDate_FMT_FORMAT"/>
        <LABEL
          ResId="com.pq.tracs.model.vo.KeyAccountActionView.EventDate_LABEL"/>
      </SchemaBasedProperties>
    </Properties>
  </ViewAttribute>
  <ViewAttribute
    Name="Description"
    PrecisionRule="true"
    EntityAttrName="Description"
    EntityUsage="TraxEvent"
    AliasName="DESCRIPTION">
    <Properties>
      <SchemaBasedProperties>
        <LABEL
          ResId="com.pq.tracs.model.vo.KeyAccountActionView.Description_LABEL"/>
        <DISPLAYWIDTH
          Value="30"/>
      </SchemaBasedProperties>
    </Properties>
  </ViewAttribute>
  <ViewAttribute
    Name="Note"
    PrecisionRule="true"
    EntityAttrName="Note"
    EntityUsage="TraxEvent"
    AliasName="NOTE">
    <Properties>
      <SchemaBasedProperties>
        <DISPLAYWIDTH
          Value="30"/>
      </SchemaBasedProperties>
    </Properties>
  </ViewAttribute>
  <ViewAttribute
    Name="CreatedBy"
    IsNotNull="true"
    PrecisionRule="true"
    EntityAttrName="CreatedBy"
    EntityUsage="TraxEvent"
    AliasName="CREATED_BY"
    IsUpdateable="false">
    <Properties>
      <SchemaBasedProperties>
        <LABEL
          ResId="com.pq.tracs.model.vo.KeyAccountActionView.CreatedBy_LABEL"/>
      </SchemaBasedProperties>
    </Properties>
  </ViewAttribute>
  <ViewAttribute
    Name="CreatedDate"
    IsUpdateable="false"
    IsNotNull="true"
    PrecisionRule="true"
    EntityAttrName="CreatedDate"
    EntityUsage="TraxEvent"
    AliasName="CREATED_DATE">
    <Properties>
      <SchemaBasedProperties>
        <LABEL
          ResId="com.pq.tracs.model.vo.KeyAccountActionView.CreatedDate_LABEL"/>
      </SchemaBasedProperties>
    </Properties>
  </ViewAttribute>
  <ViewAttribute
    Name="LastUpdatedBy"
    IsNotNull="true"
    PrecisionRule="true"
    EntityAttrName="LastUpdatedBy"
    EntityUsage="TraxEvent"
    AliasName="LAST_UPDATED_BY"
    IsUpdateable="false">
    <Properties>
      <SchemaBasedProperties>
        <LABEL
          ResId="com.pq.tracs.model.vo.KeyAccountActionView.LastUpdatedBy_LABEL"/>
      </SchemaBasedProperties>
    </Properties>
  </ViewAttribute>
  <ViewAttribute
    Name="LastUpdatedDate"
    IsUpdateable="false"
    IsNotNull="true"
    PrecisionRule="true"
    EntityAttrName="LastUpdatedDate"
    EntityUsage="TraxEvent"
    AliasName="LAST_UPDATED_DATE">
    <Properties>
      <SchemaBasedProperties>
        <LABEL
          ResId="com.pq.tracs.model.vo.KeyAccountActionView.LastUpdatedDate_LABEL"/>
      </SchemaBasedProperties>
    </Properties>
  </ViewAttribute>
  <ViewAttribute
    Name="Id1"
    IsNotNull="true"
    PrecisionRule="true"
    EntityAttrName="Id"
    EntityUsage="TraxEvent"
    AliasName="ID1"/>
  <ViewCriteria
    Name="KeyAccountActionViewCriteria"
    ViewObjectName="com.pq.tracs.model.vo.KeyAccountActionView"
    Conjunction="AND">
    <Properties>
      <CustomProperties>
        <Property
          Name="displayOperators"
          Value="InAdvancedMode"/>
        <Property
          Name="autoExecute"
          Value="false"/>
        <Property
          Name="allowConjunctionOverride"
          Value="true"/>
        <Property
          Name="showInList"
          Value="true"/>
        <Property
          Name="mode"
          Value="Basic"/>
      </CustomProperties>
    </Properties>
    <ViewCriteriaRow
      Name="vcrow5"
      UpperColumns="1">
      <ViewCriteriaItem
        Name="KeyAccountActionViewCriteria_vcrow5_EventType"
        ViewAttribute="EventType"
        Operator="STARTSWITH"
        Conjunction="AND"
        Required="Optional"/>
      <ViewCriteriaItem
        Name="KeyAccountActionViewCriteria_vcrow5_EventName"
        ViewAttribute="EventName"
        Operator="STARTSWITH"
        Conjunction="AND"
        Required="Optional"/>
      <ViewCriteriaItem
        Name="KeyAccountActionViewCriteria_vcrow5_EventDate"
        ViewAttribute="EventDate"
        Operator="="
        Conjunction="AND"
        Required="Optional"/>
      <ViewCriteriaItem
        Name="KeyAccountActionViewCriteria_vcrow5_CreatedBy"
        ViewAttribute="CreatedBy"
        Operator="STARTSWITH"
        Conjunction="AND"
        Required="Optional"/>
      <ViewCriteriaItem
        Name="KeyAccountActionViewCriteria_vcrow5_CreatedDate"
        ViewAttribute="CreatedDate"
        Operator="="
        Conjunction="AND"
        Required="Optional"/>
      <ViewCriteriaItem
        Name="KeyAccountActionViewCriteria_vcrow5_LastUpdatedBy"
        ViewAttribute="LastUpdatedBy"
        Operator="STARTSWITH"
        Conjunction="AND"
        Required="Optional"/>
      <ViewCriteriaItem
        Name="KeyAccountActionViewCriteria_vcrow5_LastUpdatedDate"
        ViewAttribute="LastUpdatedDate"
        Operator="="
        Conjunction="AND"
        Required="Optional"/>
    </ViewCriteriaRow>
  </ViewCriteria>
  <ResourceBundle>
    <PropertiesBundle
      PropertiesFile="com.pq.tracs.model.ModelBundle"/>
  </ResourceBundle>
</ViewObject>
